Metadata-Version: 2.1
Name: bokeh-wordcloud2
Version: 0.9.1
Summary: a bokeh extension that implements a wordcloud (https://wordcloud2-js.timdream.org)
Home-page: https://bokeh-wordcloud2.readthedocs.io
Author: joran beasley
Author-email: joranbeasley@gmail.com
License: GPL
Platform: UNKNOWN
Classifier: Programming Language :: Python :: 3
Classifier: Programming Language :: Python :: 3.6
Classifier: Programming Language :: Python :: 3.7
Classifier: Programming Language :: Python :: 2.7
Classifier: Operating System :: OS Independent
Classifier: Intended Audience :: Developers
Classifier: Intended Audience :: Information Technology
Classifier: Intended Audience :: Other Audience
Classifier: License :: Freely Distributable
Classifier: Topic :: Scientific/Engineering :: Information Analysis
Classifier: Topic :: Software Development :: Widget Sets
